fast_api_bala1/__init__.py
fast_api_bala1/add.py
fast_api_bala1/main.py
fast_api_bala1-0.1.3.dist-info/METADATA
fast_api_bala1-0.1.3.dist-info/WHEEL
fast_api_bala1-0.1.3.dist-info/RECORD
