Metadata-Version: 2.1
Name: fast-api-bala1
Version: 0.1.3
Summary: 
Author: Your Name
Author-email: you@example.com
Requires-Python: >=3.11,<4.0
Classifier: Programming Language :: Python :: 3
Classifier: Programming Language :: Python :: 3.11
Classifier: Programming Language :: Python :: 3.12
Requires-Dist: fastapi (>=0.109.0,<0.110.0)
Requires-Dist: uvicorn (>=0.26.0,<0.27.0)
